{
  "page_hash": "649676167e94112b7947876a3cfedefaa6d4a8fc5330f208fcec57d147946f3c",
  "paragraphs": [
    {
      "type": "text",
      "text": "Vous décidez de ne pas vous attarder davantage dans cette salle d'étude où la chute d'une plume aurait tôt fait de déclencher une catastrophe ! Évitant de faire le moindre bruit, vous retournez à la porte par laquelle vous êtes entré. Au moment où vous allez mettre la main sur la poignée, un rayon de lumière vient frapper un objet métallique tout près de la porte. Vous découvrez un panneau auquel vous tourniez le dos tout à l'heure : à côté de l'entrée, un trousseau de clefs est accroché sur une plaque de marbre rose. Il contient trois clefs : une clef de bronze, une clef taillée dans une pierre verte, probablement du jade, et une troisième forgée d'un métal inconnu. Au-dessus du panneau de marbre, une clochette d'or monte une garde immuable."
    },
    {
      "type": "link",
      "text": "Allez-vous sortir sans rien toucher,",
      "hash": "a15444e2c1fc4be1a03e55ed7916a7ebacce1675aebb790f726b9252c7772828"
    },
    {
      "type": "link",
      "text": "prendre le trousseau de clefs",
      "hash": "9de4098437c780da6851a536a2adfc64b73293ddf486a4c7ecba0625cc73aac2"
    },
    {
      "type": "link",
      "text": "ou sonner la cloche ?",
      "hash": "e59e61a16c8d117df4a219d27db733125d28793f7f8191593e6d2fe0d956ce93"
    }
  ],
  "monsters": [

  ]
}
