{
  "text": [
    {
      "type": "text",
      "text": "L'Apothicaire vous regarde glisser la fiole dans votre sac. Il réfléchit un instant, puis ajoute : « Si vous le désirez, je puis également vous céder une autre préparation parmi les trois qui se trouvent ici. » Il souffle sur l'épaisse couche de poussière qui recouvre trois flacons colorés et les pose devant lui. «Malheureusement, j'ai oublié à quoi ils pouvaient être utiles. Pour cette raison, il ne vous en coûtera qu'une pièce d'or. »"
    },
    {
      "type": "text",
      "text": "Quelle fiole voulez-vous prendre?"
    },
    {
      "type": "link",
      "text": "La bleue?",
      "hash": "36857c56527fbd2f64dd040fd33ce58dee386f36ab4fd6e304ef08831432bb5d"
    },
    {
      "type": "link",
      "text": "La jaune ?",
      "hash": "a13740467c1350bfb12bcb93bfdb765681d6b25954e8e56c78641b56470c5cfd"
    },
    {
      "type": "link",
      "text": "La verte?",
      "hash": "b84d0a1cb0dc036a4773a06adf3f9098b9b615129b99482ace4858cd6f5c49e8"
    },
    {
      "type": "link",
      "text": "Si vous n'avez pas d'argent ou préférez ne pas le gaspiller sur des objets dont vous ignorez l'usage.",
      "hash": "2cb78d0ed943221b55222aa494f856f1cf702807ca634ffbcc5b9e15a41eb587"
    }
  ],
  "monsters": [

  ]
}
